ramanchada2/__init__.py
ramanchada2/__main__.py
ramanchada2/auxiliary/__init__.py
ramanchada2/auxiliary/spectra/__init__.py
ramanchada2/auxiliary/spectra/datasets2/__init__.py
ramanchada2/auxiliary/spectra/datasets2/FMNT-M_BW532/LED532_Probe_40msx3_1.txt
ramanchada2/auxiliary/spectra/datasets2/FMNT-M_BW532/NIST532_Probe_3000msx8_1.txt
ramanchada2/auxiliary/spectra/datasets2/FMNT-M_BW532/NeonSNQ043_iR532_Probe_100msx2.txt
ramanchada2/auxiliary/spectra/datasets2/FMNT-M_BW532/NeonSNQ043_iR532_Probe_5msx2.txt
ramanchada2/auxiliary/spectra/datasets2/FMNT-M_BW532/PST10_iR532_Probe_100_3000msx7.txt
ramanchada2/auxiliary/spectra/datasets2/FMNT-M_BW532/S0B10_iR532_Probe_100_60000msx2.txt
ramanchada2/auxiliary/spectra/datasets2/FMNT-M_BW532/S0N10_iR532_Probe_100_30000msx3.txt
ramanchada2/auxiliary/spectra/datasets2/FMNT-M_BW532/S0P10_iR532_Probe_100_60000msx2.txt
ramanchada2/auxiliary/spectra/datasets2/FMNT-M_BW532/S1N10_iR532_Probe_100_22000msx2.txt
ramanchada2/auxiliary/spectra/datasets2/FMNT-M_BW532/Sil10_iR532_Probe_100_60000msx2.txt
ramanchada2/auxiliary/spectra/datasets2/FMNT-M_BW532/nCAL10_iR532_Probe_100_2500msx3.txt
ramanchada2/auxiliary/spectra/datasets2/FMNT-M_BW532/sCAL10_iR532_Probe_100_3200msx4.txt
ramanchada2/auxiliary/spectra/datasets2/FMNT-M_Ho785/LED785_Lens_1000x10_2.txt
ramanchada2/auxiliary/spectra/datasets2/FMNT-M_Ho785/NIST785_Lens_80000x5_2.txt
ramanchada2/auxiliary/spectra/datasets2/FMNT-M_Ho785/NeonSNQ043_iR785_OP01.txt
ramanchada2/auxiliary/spectra/datasets2/FMNT-M_Ho785/NeonSNQ043_iR785_OP02.txt
ramanchada2/auxiliary/spectra/datasets2/FMNT-M_Ho785/NeonSNQ043_iR785_OP03.txt
ramanchada2/auxiliary/spectra/datasets2/FMNT-M_Ho785/PST10_iR785_OP01_40000msx4.txt
ramanchada2/auxiliary/spectra/datasets2/FMNT-M_Ho785/PST10_iR785_OP02_50000msx2.txt
ramanchada2/auxiliary/spectra/datasets2/FMNT-M_Ho785/PST10_iR785_OP03_8000msx2.txt
ramanchada2/auxiliary/spectra/datasets2/FMNT-M_Ho785/S0B10_iR785_OP01_6000msx4.txt
ramanchada2-1.3.1.dist-info/licenses/LICENSE
ramanchada2-1.3.1.dist-info/METADATA
ramanchada2-1.3.1.dist-info/WHEEL
ramanchada2-1.3.1.dist-info/entry_points.txt
ramanchada2-1.3.1.dist-info/top_level.txt
ramanchada2-1.3.1.dist-info/RECORD
