Metadata-Version: 2.4
Name: ramanchada2
Version: 1.3.1
Summary: Harmonising Raman Spectroscopy
Home-page: https://github.com/h2020charisma/ramanchada2
Author: IDEAconsult Ltd.
Author-email: dev-charisma@ideaconsult.net
License: MIT
Keywords: Raman,spectroscopy
Classifier: Development Status :: 5 - Production/Stable
Classifier: Intended Audience :: Developers
Classifier: Intended Audience :: Education
Classifier: Intended Audience :: Science/Research
Classifier: License :: OSI Approved :: MIT License
Classifier: Operating System :: OS Independent
Classifier: Programming Language :: Python :: 3 :: Only
Classifier: Programming Language :: Python :: 3
Classifier: Programming Language :: Python
Classifier: Topic :: Scientific/Engineering :: Bio-Informatics
Classifier: Topic :: Scientific/Engineering
Classifier: Topic :: Software Development :: Libraries :: Python Modules
Classifier: Topic :: Software Development :: Libraries
Requires-Python: >=3.9,<3.14
License-File: LICENSE
Requires-Dist: brukeropusreader==1.*
Requires-Dist: h5py==3.*
Requires-Dist: lmfit==1.*
Requires-Dist: matplotlib==3.*
Requires-Dist: numpy<3.0,>=1.0
Requires-Dist: pandas==2.*
Requires-Dist: pydantic~=2.0
Requires-Dist: emd==0.7.*
Requires-Dist: renishawWiRE==0.1.*
Requires-Dist: scikit-learn==1.*
Requires-Dist: scipy<2.0,>=1.8.0
Requires-Dist: spc-io~=0.2.0
Requires-Dist: statsmodels==0.14.*
Requires-Dist: uncertainties==3.*
Requires-Dist: spe2py~=2.0
Dynamic: author
Dynamic: author-email
Dynamic: classifier
Dynamic: description
Dynamic: description-content-type
Dynamic: home-page
Dynamic: keywords
Dynamic: license
Dynamic: license-file
Dynamic: requires-dist
Dynamic: requires-python
Dynamic: summary
